specifications/__init__.py
specifications/common.py
specifications/merkletree.py
pycelium_specifications-0.0.2.2.dist-info/METADATA
pycelium_specifications-0.0.2.2.dist-info/WHEEL
pycelium_specifications-0.0.2.2.dist-info/licenses/license
pycelium_specifications-0.0.2.2.dist-info/RECORD
