Metadata-Version: 2.1
Name: pycelium-specifications
Version: 0.0.2.2
Summary: Library of common interfaces for the Pycelium project.
Project-URL: Homepage, https://github.com/k98kurz/pycelium-specifications
Project-URL: Bug Tracker, https://github.com/k98kurz/pycelium-specifications/issues
Author-email: k98kurz <k98kurz@gmail.com>
License-File: license
Classifier: License :: OSI Approved :: ISC License (ISCL)
Classifier: Operating System :: OS Independent
Classifier: Programming Language :: Python :: 3
Classifier: Topic :: Office/Business :: Financial
Classifier: Topic :: Security :: Cryptography
Classifier: Topic :: System :: Distributed Computing
Classifier: Topic :: System :: Networking
Requires-Python: >=3.7
